{"is_source_file": false, "format": "", "description": "", "external_files": [], "external_methods": [], "published": [], "classes": [], "methods": [], "calls": [], "search-terms": [], "state": 2, "file_id": 7, "knowledge_revision": 51, "git_revision": "f9607890437ce7f4632617ea8a97c8c651d7fe2a", "hash": "77d2a8926bce7372db014533847a407f", "format-version": 4, "code-base-name": "note_taking_frontend", "filename": "note_taking_frontend/src/routes/styles.css", "revision_history": [{"51": "f9607890437ce7f4632617ea8a97c8c651d7fe2a"}]}