{"is_source_file": true, "format": "md", "description": ".md file: README.md", "external_files": [], "external_methods": [], "published": [], "classes": [], "methods": [], "calls": [], "search-terms": ["README.md", "md"], "state": 2, "file_id": 17, "knowledge_revision": 73, "git_revision": "1e71d6d3f7314b0e924e0c528195385c684d077b", "revision_history": [{"29": "1e71d6d3f7314b0e924e0c528195385c684d077b"}, {"73": "1e71d6d3f7314b0e924e0c528195385c684d077b"}], "filename": "README.md", "format-version": 4, "code-base-name": "https://github.com/kavia-common/simple-notes-app-42745-42754.git:kavia-main"}